cryptodatapy/__init__.py
cryptodatapy/conf/__init__.py
cryptodatapy/conf/fields.csv
cryptodatapy/conf/tickers.csv
cryptodatapy/core/data_client.py
cryptodatapy/core/data_request.py
cryptodatapy/extract/__init__.py
cryptodatapy/extract/adapters/__init__.py
cryptodatapy/extract/adapters/base_adapter.py
cryptodatapy/extract/adapters/exchanges/__init__.py
cryptodatapy/extract/adapters/libraries/__init__.py
cryptodatapy/extract/adapters/libraries/ccxt_adapter.py
cryptodatapy/extract/adapters/vendors/__init__.py
cryptodatapy/extract/adapters/vendors/base_api_vendor.py
cryptodatapy/extract/adapters/vendors/coinmetrics_adapter.py
cryptodatapy/extract/adapters/vendors/defillama_adapter.py
cryptodatapy/extract/adapters/web/__init__.py
cryptodatapy/extract/config/__init__.py
cryptodatapy/extract/config/coinmetrics_config.py
cryptodatapy/extract/config/defillama_config.py
cryptodatapy/extract/data_vendors/.ipynb_checkpoints/CCXT-checkpoint.ipynb
cryptodatapy/extract/data_vendors/.ipynb_checkpoints/DBNomics-checkpoint.ipynb
cryptodatapy/extract/data_vendors/.ipynb_checkpoints/InvestPy-checkpoint.ipynb
cryptodatapy/extract/data_vendors/.ipynb_checkpoints/NasdaqDataLink-checkpoint.ipynb
cryptodatapy/extract/data_vendors/.ipynb_checkpoints/PandasDataReader-checkpoint.ipynb
cryptodatapy/extract/data_vendors/__init__.py
cryptodatapy/extract/data_vendors/coinmetrics_api.py
cryptodatapy/extract/data_vendors/cryptocompare_api.py
cryptodatapy/extract/data_vendors/datavendor.py
cryptodatapy/extract/data_vendors/glassnode_api.py
cryptodatapy/extract/data_vendors/polygon_api.py
cryptodatapy/extract/data_vendors/tiingo_api.py
cryptodatapy/extract/datarequest.py
cryptodatapy/extract/exchanges/__init__.py
cryptodatapy/extract/exchanges/dydx.py
cryptodatapy/extract/exchanges/exchange.py
cryptodatapy/extract/getdata.py
cryptodatapy/extract/libraries/__init__.py
cryptodatapy/extract/libraries/ccxt_api.py
cryptodatapy/extract/libraries/dbnomics_api.py
cryptodatapy-0.3.3.dist-info/METADATA
cryptodatapy-0.3.3.dist-info/WHEEL
cryptodatapy-0.3.3.dist-info/licenses/LICENSE
cryptodatapy-0.3.3.dist-info/RECORD
