Metadata-Version: 2.4
Name: cryptodatapy
Version: 0.3.3
Summary: Cryptoasset data library
License: Apache-2.0
License-File: LICENSE
Author: Systamental
Requires-Python: >=3.9,<4.0
Classifier: License :: OSI Approved :: Apache Software License
Classifier: Programming Language :: Python :: 3
Classifier: Programming Language :: Python :: 3.9
Classifier: Programming Language :: Python :: 3.10
Classifier: Programming Language :: Python :: 3.11
Classifier: Programming Language :: Python :: 3.12
Classifier: Programming Language :: Python :: 3.13
Classifier: Programming Language :: Python :: 3.14
Requires-Dist: DBnomics (>=1.2.3)
Requires-Dist: ccxt (>=1.91.52)
Requires-Dist: coinmetrics-api-client (==2024.12.23.19) ; python_version >= "3.7"
Requires-Dist: cryptodatapy-pandas-datareader (>=0.10.1)
Requires-Dist: fsspec (>=2024.6.1)
Requires-Dist: matplotlib (>=3.5.2)
Requires-Dist: numpy (>=1.23.2)
Requires-Dist: openpyxl (>=3.1.2)
Requires-Dist: pandas (>=2.2.3)
Requires-Dist: polygon-api-client (>=1.14.6)
Requires-Dist: prophet (>=1.1) ; python_version >= "3.7"
Requires-Dist: pyarrow (>=17.0.0)
Requires-Dist: requests (>=2.28.0) ; python_version >= "3.7"
Requires-Dist: responses (>=0.21.0)
Requires-Dist: s3fs (>=2024.6.1)
Requires-Dist: selenium (>=4.4.3)
Requires-Dist: statsmodels (>=0.13.2)
Requires-Dist: tdqm (>=0.0.1)
Requires-Dist: webdriver-manager (>=3.8.3)
Requires-Dist: xlrd (>=2.0.1)
Requires-Dist: yfinance (==0.2.64)
